<?xml version="1.0" ?>
<?mso-application progid="Excel.Sheet"?>
<Workbook
  xmlns="urn:schemas-microsoft-com:office:spreadsheet"
  xmlns:o="urn:schemas-microsoft-com:office:office"
  xmlns:x="urn:schemas-microsoft-com:office:excel"
  xmlns:ss="urn:schemas-microsoft-com:office:spreadsheet"
  xmlns:html="http://www.w3.org/TR/REC-html40"
><DocumentProperties xmlns="urn:schemas-microsoft-com:office:office"><LastAuthor
    >Luis Ferreira</LastAuthor><LastSaved
    >2019-01-31T09:58:03Z</LastSaved><Version
    >16.00</Version></DocumentProperties><OfficeDocumentSettings
    xmlns="urn:schemas-microsoft-com:office:office"
  ><AllowPNG /></OfficeDocumentSettings><ExcelWorkbook
    xmlns="urn:schemas-microsoft-com:office:excel"
  ><WindowHeight>10920</WindowHeight><WindowWidth>19365</WindowWidth><WindowTopX
    >32767</WindowTopX><WindowTopY>32767</WindowTopY><RefModeR1C1
    /><ProtectStructure>False</ProtectStructure><ProtectWindows
    >False</ProtectWindows></ExcelWorkbook><Styles><Style
      ss:ID="Default"
      ss:Name="Normal"
    ><Alignment ss:Vertical="Bottom" /><Borders /><Font
        ss:FontName="Calibri"
        x:Family="Swiss"
        ss:Size="11"
        ss:Color="#000000"
      /><Interior /><NumberFormat /><Protection /></Style><Style
      ss:ID="s62"
      ss:Name="Hyperlink"
    ><Font
        ss:FontName="Calibri"
        x:Family="Swiss"
        ss:Size="11"
        ss:Color="#0066CC"
        ss:Underline="Single"
      /></Style><Style ss:ID="s63"><Alignment
        ss:Vertical="Top"
        ss:WrapText="1"
      /></Style><Style ss:ID="s65" ss:Parent="s62"><Alignment
        ss:Vertical="Top"
        ss:WrapText="1"
      /></Style></Styles><Worksheet ss:Name="Script"><Table
      x:FullColumns="1"
      x:FullRows="1"
      ss:StyleID="s63"
      ss:DefaultColumnWidth="348"
      ss:DefaultRowHeight="15"
    ><Column ss:StyleID="s63" ss:Width="141.75" /><Column
        ss:StyleID="s63"
        ss:Width="87"
      /><Column ss:StyleID="s63" ss:Width="300.75" /><Column
        ss:StyleID="s63"
        ss:Width="147.75"
      /><Column ss:StyleID="s63" ss:Width="213.75" /><Column
        ss:StyleID="s63"
        ss:Width="120"
      /><Row ss:AutoFitHeight="0" ss:Height="90"><Cell><Data
            ss:Type="String"
          >UNITPROPERTIES_STRATEGIC_DLC04</Data></Cell><Cell ss:Index="7"><Data
            ss:Type="String"
          >The DEV TEAM / MISC NOTES column contains info on what text between { } signs means (if applicable). It usually stands for either a numeric value, or a numeric value with an icon. Text between [ ] signs stands for a certain type of icon. </Data></Cell></Row><Row
        ss:AutoFitHeight="0"
      ><Cell><Data ss:Type="String">SCENE ID</Data></Cell><Cell><Data
            ss:Type="String"
          >TEXT ID</Data></Cell><Cell><Data
            ss:Type="String"
          >ENGLISH STRING</Data></Cell><Cell><Data
            ss:Type="String"
          >LOCALIZED STRING</Data></Cell><Cell><Data
            ss:Type="String"
          >ALTERNATIVE ENGLISH STRING</Data></Cell><Cell><Data
            ss:Type="String"
          >ALTERNATIVE LOCALIZED STRING</Data></Cell><Cell><Data
            ss:Type="String"
          >LOCALIZATION NOTES</Data></Cell><Cell><Data
            ss:Type="String"
          >DEV TEAM / MISC NOTES</Data></Cell></Row><Row
        ss:AutoFitHeight="0"
      ><Cell><Data ss:Type="String">FOUND_SHAKARN_COLONY</Data></Cell><Cell
        ><Data ss:Type="String">NAME</Data></Cell><Cell><Data
            ss:Type="String"
          >[colony/] Found Shakarn Colony</Data></Cell><Cell><Data
            ss:Type="String"
          >[colony/]建立蜥蜴人殖民地</Data></Cell><Cell ss:Index="7"><Data
            ss:Type="String"
          >Shakarn is player race</Data></Cell></Row><Row
        ss:AutoFitHeight="0"
        ss:Height="60"
      ><Cell><Data ss:Type="String">FOUND_SHAKARN_COLONY</Data></Cell><Cell
        ><Data ss:Type="String">DESCRIPTION</Data></Cell><Cell
          ss:StyleID="s65"
          ss:HRef="mailto:%7BXML_UNITPROPERTIES_STRATEGIC@FOUND_COLONY@SHARED_DESCRIPTION%7D"
        ><Data
            ss:Type="String"
          >{XML_UNITPROPERTIES_STRATEGIC@FOUND_COLONY@SHARED_DESCRIPTION}</Data></Cell><Cell
        ><Data
            ss:Type="String"
          >{XML_UNITPROPERTIES_STRATEGIC@FOUND_COLONY@SHARED_DESCRIPTION}</Data></Cell><Cell
          ss:Index="7"
        ><Data ss:Type="String">Don't Translate</Data></Cell></Row><Row><Cell
        ><Data ss:Type="String" /></Cell><Cell><Data
            ss:Type="String"
          /></Cell><Cell><Data ss:Type="String" /></Cell><Cell
          ss:Index="7"
        ><Data
            ss:Type="String"
          >In the text below, text refers to a person that can either be male or female. If relevant for translation, please use the ‘localized string’ column for the male text and the ‘alternative localized string’ column for the female text. You and Your might be examples of this.</Data></Cell></Row><Row
      ><Cell><Data ss:Type="String" /></Cell><Cell><Data
            ss:Type="String"
          /></Cell><Cell><Data ss:Type="String" /></Cell><Cell
          ss:Index="7"
        ><Data
            ss:Type="String"
          >In the text below, any inserted strings - anything of the form {text} - is replaced by an integer value for the thing described in the brackets. If the {text} is not followed by a unit - e.g. shields, hitpoints - the icon for the unit is inserted together with the integer. The same holds for symbols - e.g. '+', '%' - which are occasionally inserted together with the integer.</Data></Cell></Row><Row
      ><Cell><Data ss:Type="String" /></Cell><Cell><Data
            ss:Type="String"
          /></Cell><Cell><Data ss:Type="String" /></Cell><Cell
          ss:Index="7"
        ><Data
            ss:Type="String"
          >For references to game terminology and in-world references, please check the glossary delivered as part of the documentation.</Data></Cell></Row></Table><WorksheetOptions
      xmlns="urn:schemas-microsoft-com:office:excel"
    ><Unsynced /><Selected /><Panes><Pane><Number>3</Number><ActiveRow
          >6</ActiveRow><ActiveCol>5</ActiveCol></Pane></Panes><ProtectObjects
      >False</ProtectObjects><ProtectScenarios
      >False</ProtectScenarios></WorksheetOptions></Worksheet></Workbook>
